Metadata-Version: 2.1
Name: odoo13-addon-shipment-advice
Version: 13.0.1.3.0
Summary: Manage your (un)loading process through shipment advices.
Home-page: https://github.com/OCA/stock-logistics-transport
Author: Camptocamp, Odoo Community Association (OCA)
Author-email: support@odoo-community.org
License: AGPL-3
Platform: UNKNOWN
Classifier: Programming Language :: Python
Classifier: Framework :: Odoo
Classifier: Framework :: Odoo :: 13.0
Classifier: License :: OSI Approved :: GNU Affero General Public License v3
Requires-Python: >=3.5
Requires-Dist: odoo13-addon-stock-dock
Requires-Dist: odoo (<13.1dev,>=13.0a)
